{
  "collectionName": "components_seo_seos",
  "info": {
    "displayName": "seo",
    "icon": "search"
  },
  "options": {},
  "attributes": {
    "metaTitle": {
      "type": "string",
      "required": true
    },
    "metaDescription": {
      "type": "string",
      "required": true,
      "maxLength": 160,
      "minLength": 50
    },
    "metaImage": {
      "type": "media",
      "multiple": false,
      "required": false,
      "allowedTypes": [
        "images"
      ]
    },
    "openGraph": {
      "type": "component",
      "repeatable": false,
      "component": "seo.open-graph"
    },
    "keywords": {
      "type": "text",
      "regex": "[^,]+"
    },
    "metaRobots": {
      "type": "string",
      "regex": "[^,]+"
    },
    "metaViewport": {
      "type": "string"
    },
    "canonicalURL": {
      "type": "string"
    },
    "structuredData": {
      "type": "json"
    }
  },
  "config": {}
}
